loginpass/__init__.py
loginpass/_consts.py
loginpass/_core.py
loginpass/_django.py
loginpass/_fastapi.py
loginpass/_flask.py
loginpass/auth0.py
loginpass/azure.py
loginpass/battlenet.py
loginpass/bitbucket.py
loginpass/discord.py
loginpass/dropbox.py
loginpass/facebook.py
loginpass/github.py
loginpass/gitlab.py
loginpass/google.py
loginpass/hydra.py
loginpass/instagram.py
loginpass/linkedin.py
loginpass/orcid.py
loginpass/reddit.py
loginpass/slack.py
loginpass/spotify.py
loginpass/stackapps.py
loginpass/strava.py
loginpass/twitch.py
loginpass/twitter.py
loginpass/vk.py
loginpass/yandex.py
iloginpass-0.5.dist-info/LICENSE
iloginpass-0.5.dist-info/METADATA
iloginpass-0.5.dist-info/WHEEL
iloginpass-0.5.dist-info/top_level.txt
iloginpass-0.5.dist-info/RECORD
